intelino/trainlib/__init__.py
intelino/trainlib/enums.py
intelino/trainlib/exc.py
intelino/trainlib/helpers.py
intelino/trainlib/messages.py
intelino/trainlib/train.py
intelino/trainlib/train_scanner.py
intelino_trainlib-1.0.0.dist-info/LICENSE
intelino_trainlib-1.0.0.dist-info/METADATA
intelino_trainlib-1.0.0.dist-info/WHEEL
intelino_trainlib-1.0.0.dist-info/top_level.txt
intelino_trainlib-1.0.0.dist-info/RECORD
