Metadata-Version: 2.1
Name: intelino-trainlib
Version: 1.0.0
Summary: Python library (SDK) for interacting with the intelino smart train.
Home-page: https://intelino.com
Author: intelino
Author-email: developer@intelino.com
License: Intelino Public License
Project-URL: Documentation, https://intelino-trainlib-py.readthedocs.io/
Project-URL: Source Code, https://github.com/intelino-code/intelino-trainlib-py
Project-URL: Examples, https://github.com/intelino-code/intelino-trainlib-py-examples
Project-URL: Intelino Lab, https://lab.intelino.com
Platform: UNKNOWN
Classifier: Intended Audience :: Developers
Classifier: Intended Audience :: Education
Classifier: License :: Other/Proprietary License
Classifier: Operating System :: Microsoft :: Windows :: Windows 10
Classifier: Operating System :: POSIX :: Linux
Classifier: Operating System :: MacOS :: MacOS X
Classifier: Programming Language :: Python
Classifier: Programming Language :: Python :: 3
Classifier: Programming Language :: Python :: 3.7
Classifier: Programming Language :: Python :: 3.8
Classifier: Programming Language :: Python :: 3.9
Classifier: Programming Language :: Python :: 3 :: Only
Classifier: Typing :: Typed
Requires-Python: >=3.7
License-File: LICENSE
Requires-Dist: intelino-trainlib-async
